lfview/__init__.py
lfview/client/__init__.py
lfview/client/constants.py
lfview/client/session.py
lfview/client/utils.py
lfview/client/convert/__init__.py
lfview/client/convert/omf.py
lfview/client/convert/steno3d.py
lfview_api_client-0.1.2.dist-info/METADATA
lfview_api_client-0.1.2.dist-info/WHEEL
lfview_api_client-0.1.2.dist-info/top_level.txt
lfview_api_client-0.1.2.dist-info/RECORD
