Metadata-Version: 2.1
Name: lfview-api-client
Version: 0.1.2
Summary: Python client for LF View API
Home-page: https://lfview.com
Author: Seequent
Author-email: franklin.koch@seequent.com
License: MIT
Download-URL: https://github.com/seequent/lfview-api-client
Platform: Windows
Platform: Linux
Platform: Solaris
Platform: Mac OS-X
Platform: Unix
Classifier: Development Status :: 4 - Beta
Classifier: Programming Language :: Python :: 2.7
Classifier: Programming Language :: Python :: 3.6
Classifier: License :: OSI Approved :: MIT License
Classifier: Topic :: Scientific/Engineering
Classifier: Operating System :: Microsoft :: Windows
Classifier: Operating System :: POSIX
Classifier: Operating System :: Unix
Classifier: Operating System :: MacOS
Classifier: Natural Language :: English
Requires-Dist: requests
Requires-Dist: properties[full] (>=0.5.6)
Requires-Dist: omf (==1.0.1)
Requires-Dist: steno3d
Requires-Dist: lfview-resources-files (==0.0.2)
Requires-Dist: lfview-resources-spatial (==0.0.6)
Requires-Dist: lfview-resources-manifests (==0.0.1)
Requires-Dist: lfview-resources-scene (==0.0.1)
Requires-Dist: futures ; python_version == "2.7"
Provides-Extra: omf
Requires-Dist: omf ; extra == 'omf'
Requires-Dist: steno3d ; extra == 'omf'
Provides-Extra: steno3d
Requires-Dist: steno3d ; extra == 'steno3d'
